pydantic_duality/__init__.py
pydantic_duality/py.typed
pydantic_duality-2.0.2.dist-info/LICENSE
pydantic_duality-2.0.2.dist-info/METADATA
pydantic_duality-2.0.2.dist-info/WHEEL
pydantic_duality-2.0.2.dist-info/RECORD
