Metadata-Version: 2.1
Name: pydantic-duality
Version: 2.0.2
Summary: Automatically generate two versions of your pydantic models: one with Extra.forbid and one with Extra.ignore
Home-page: https://github.com/zmievsa/pydantic-duality
License: MIT
Author: Stanislav Zmiev
Author-email: zmievsa@gmail.com
Requires-Python: >=3.9,<4.0
Classifier: License :: OSI Approved :: MIT License
Classifier: Programming Language :: Python :: 3
Classifier: Programming Language :: Python :: 3.9
Classifier: Programming Language :: Python :: 3.10
Classifier: Programming Language :: Python :: 3.11
Classifier: Programming Language :: Python :: 3.12
Requires-Dist: cached-classproperty (>=0.1.0)
Requires-Dist: pydantic (>=2.0.0,<3.0.0)
Requires-Dist: typing-extensions (>=4.8.0)
Project-URL: Repository, https://github.com/zmievsa/pydantic-duality
